hopthru_api_client/__init__.py
hopthru_api_client/__version__.py
hopthru_api_client/apc_data.py
hopthru_api_client/client.py
hopthru_api_client/config.py
hopthru_api_client/dates.py
hopthru_api_client/logging.py
hopthru_api_client/types.py
hopthru_api_python_client-0.22.0.dist-info/LICENSE
hopthru_api_python_client-0.22.0.dist-info/METADATA
hopthru_api_python_client-0.22.0.dist-info/WHEEL
hopthru_api_python_client-0.22.0.dist-info/top_level.txt
hopthru_api_python_client-0.22.0.dist-info/RECORD
