Metadata-Version: 2.1
Name: hopthru-api-python-client
Version: 0.22.0
Summary: The Hopthru API Python Client
Home-page: https://github.com/Hopthru/hopthru-api-python-client
Author: Hopthru
Author-email: brock@hopthru.com
Classifier: Programming Language :: Python :: 3
Classifier: License :: OSI Approved :: MIT License
Classifier: Operating System :: OS Independent
Requires-Python: >=3.7
License-File: LICENSE
Requires-Dist: typing-extensions >=3.10
Requires-Dist: requests >=2.28
Requires-Dist: sentry-sdk >=1.5
Requires-Dist: structlog >=21.5
Requires-Dist: structlog-sentry <2.0,>=1.4
